[
  {
    "name": "pug1",
    "image": "/img/pug1.jpg",
    "clicked": false
  },
  {
    "name": "pug2",
    "image": "/img/pug2.jpg",
    "clicked": false
  },
  {
    "name": "pug3",
    "image": "/img/pug3.jpg",
    "clicked": false
  },
  {
    "name": "pug4",
    "image": "/img/pug4.jpg",
    "clicked": false
  },
  {
    "name": "pug5",
    "image": "/img/pug5.jpeg",
    "clicked": false
  },
  {
    "name": "pug6",
    "image": "/img/pug6.jpg",
    "clicked": false
  },
  {
    "name": "pug7",
    "image": "/img/pug7.jpg",
    "clicked": false
  },
  {
    "name": "pug8",
    "image": "/img/pug8.jpeg",
    "clicked": false
  },
  {
    "name": "pug9",
    "image": "/img/pug9.jpeg",
    "clicked": false
  },
  {
    "name": "pug10",
    "image": "/img/pug10.png",
    "clicked": false
  },
  {
    "name": "pug11",
    "image": "/img/pug11.jpg",
    "clicked": false
  },
  {
    "name": "pug12",
    "image": "/img/pug12.jpg",
    "clicked": false
  }
]
